LICENSE
README.md
setup.py
skeins/__init__.py
skeins/__main__.py
skeins/datasets.py
skeins/graph_calculus.py
skeins/graph_construction.py
skeins/graph_frequencies.py
skeins/graph_prediction.py
skeins/graph_sparsification.py
skeins/graph_utils.py
skeins/hierarchical_diffusion_embedding.py
skeins/hierarchy_tools.py
skeins/linalg_utils.py
skeins/visualization.py
skeins.egg-info/PKG-INFO
skeins.egg-info/SOURCES.txt
skeins.egg-info/dependency_links.txt
skeins.egg-info/requires.txt
skeins.egg-info/top_level.txt
tests/test_main.py